pyettj/__init__.py
pyettj/ettj.py
pyettj/Feriados.csv
pyettj/gettables.py
pyettj/modelo_ettj.py
pyettj/version.py
pyettj-0.3.3.dist-info/LICENSE.md
pyettj-0.3.3.dist-info/METADATA
pyettj-0.3.3.dist-info/WHEEL
pyettj-0.3.3.dist-info/RECORD
