Metadata-Version: 2.3
Name: pyettj
Version: 0.3.3
Summary: Coletar e tratar dados de curvas de juros (ettj).
License: MIT
Author: Rafael Rodrigues
Author-email: rafael.rafarod@gmail.com
Requires-Python: >=3.8.5,<4.0.0
Classifier: License :: OSI Approved :: MIT License
Classifier: Programming Language :: Python :: 3
Classifier: Programming Language :: Python :: 3.9
Classifier: Programming Language :: Python :: 3.10
Classifier: Programming Language :: Python :: 3.11
Classifier: Programming Language :: Python :: 3.12
Classifier: Programming Language :: Python :: 3.13
Requires-Dist: bizdays (<=1.0.13) ; python_full_version <= "3.9.0"
Requires-Dist: bizdays (>=1.0.16) ; python_version >= "3.10"
Requires-Dist: bs4 (>=0.0.2,<0.0.3)
Requires-Dist: lxml (>=5.3.0,<6.0.0)
Requires-Dist: matplotlib (<=3.7.1) ; python_full_version <= "3.9.0"
Requires-Dist: matplotlib (>=3.10.0) ; python_version >= "3.10"
Requires-Dist: nelson-siegel-svensson (>=0.5.0,<0.6.0)
Requires-Dist: numpy (<1.26.0) ; python_full_version <= "3.9.0"
Requires-Dist: numpy (>=1.26.0) ; python_version >= "3.10"
Requires-Dist: pandas (<=1.5.3) ; python_full_version <= "3.9.0"
Requires-Dist: pandas (>=2.2.3) ; python_version >= "3.10"
Requires-Dist: requests (>=2.32.3,<3.0.0)
Requires-Dist: scipy (>=1.13.1) ; python_version >= "3.9"
Requires-Dist: scipy (>=1.7,<1.9.1) ; python_version < "3.9"
